CHANGES.txt
LICENSE.txt
MANIFEST.in
README.txt
setup.py
js/__init__.py
js.mediaelement.egg-info/PKG-INFO
js.mediaelement.egg-info/SOURCES.txt
js.mediaelement.egg-info/dependency_links.txt
js.mediaelement.egg-info/entry_points.txt
js.mediaelement.egg-info/namespace_packages.txt
js.mediaelement.egg-info/not-zip-safe
js.mediaelement.egg-info/requires.txt
js.mediaelement.egg-info/top_level.txt
js/mediaelement/__init__.py
js/mediaelement/test_mediaelement.js.txt
js/mediaelement/resources/DO NOT CHANGE THESE FILES. USE -src- FOLDER.txt
js/mediaelement/resources/background.png
js/mediaelement/resources/bigplay.png
js/mediaelement/resources/bigplay.svg
js/mediaelement/resources/controls-ted.png
js/mediaelement/resources/controls-wmp-bg.png
js/mediaelement/resources/controls-wmp.png
js/mediaelement/resources/controls.png
js/mediaelement/resources/controls.svg
js/mediaelement/resources/flashmediaelement-cdn.swf
js/mediaelement/resources/flashmediaelement.swf
js/mediaelement/resources/jquery.js
js/mediaelement/resources/loading.gif
js/mediaelement/resources/mediaelement-and-player.js
js/mediaelement/resources/mediaelement-and-player.min.js
js/mediaelement/resources/mediaelement.js
js/mediaelement/resources/mediaelement.min.js
js/mediaelement/resources/mediaelementplayer.css
js/mediaelement/resources/mediaelementplayer.js
js/mediaelement/resources/mediaelementplayer.min.css
js/mediaelement/resources/mediaelementplayer.min.js
js/mediaelement/resources/mejs-skins.css
js/mediaelement/resources/silverlightmediaelement.xap