Metadata-Version: 1.0
Name: js.mediaelement
Version: 2.13.1
Summary: Fanstatic packaging of MediaElement.js
Home-page: UNKNOWN
Author: Andreas Kaiser
Author-email: disko@binary-punks.com
License: BSD
Platform: UNKNOWN
